{
  "actions": "Toimingud",
  "addReview": "Lisa arvustus",
  "addSeriesToSubscription": "Uue jao eetrisse jõudmise kohta uudiste saamiseks lisage oma tellimuste loendisse sarju.",
  "addToCurrentWatchQueue": "Lisage praegusesse vaatamise järjekorda.",
  "addToQueue": "Lisa järjekorda",
  "postAReviewForTheEpisode": "Postitage jao kohta arvustus.",
  "report": "Aruanne",
  "reportAnIssue": "Teatage probleemist/rikkumisest.",
  "selectAction": "Vali toiming",
  "subscribeToSeries": "Telli sarjad"
}
